{
	"required": true,
	"priority": 1000,
	"package": "dev.xkmc.youkaishomecoming.mixin",
	"compatibilityLevel": "JAVA_17",
	"refmap": "youkaishomecoming.refmap.json",
	"mixins": [
		"AddItemModifierAccessor",
		"AddLootTableModifierAccessor",
		"CookingPotRecipeAccessor",
		"CopyMealFunctionMixin",
		"FrogAttackablesSensorMixin",
		"ItemAccessor",
		"PlayerMixin",
		"ShootTongueMixin",
		"api.PersistentEntitySectionManagerAccessor",
		"api.ServerLevelAccessor",
		"effect.EntityMixin",
		"effect.LivingEntityMixin",
		"effect.PhantomSpawnerMixin",
		"effect.RandomizableContainerBlockEntityMixin",
		"effect.VillagerMixin",
		"structure.BeardifierMixin",
		"structure.BoundingBoxMixin",
		"structure.JigsawStructureAccessor",
		"structure.SinglePoolElementMixin"
	],
	"client": [
		"CriterionGridMixin",
		"api.BufferBuilderAccessor",
		"effect.GameRendererMixin"
	],
	"injectors": {
		"defaultRequire": 1
	},
	"minVersion": "0.8"
}
