{
  "parent": "minecraft:recipes/root",
  "criteria": {
    "has_the_recipe": {
      "conditions": {
        "recipe": "youkaisfeasts:champagne"
      },
      "trigger": "minecraft:recipe_unlocked"
    },
    "has_white_grape": {
      "conditions": {
        "items": [
          {
            "items": "youkaisfeasts:white_grape"
          }
        ]
      },
      "trigger": "minecraft:inventory_changed"
    }
  },
  "requirements": [
    [
      "has_the_recipe",
      "has_white_grape"
    ]
  ],
  "rewards": {
    "recipes": [
      "youkaisfeasts:champagne"
    ]
  }
}